{
  "titulo": "Iusto argentum beatae anser totidem commodi tantillus doloribus coruscus conqueror conitor vulariter varius.",
  "topicos": [
    "Averto animadverto subnecto statua condico tego.",
    "Acer adeptio acidus.",
    "Cibo perspiciatis modi confugo solium cupressus thermae terga.",
    "Cornu dedico compello talus curvo titulus.",
    "Casus clarus cubitum denique solvo cavus tandem iste eum quis.",
    "Comis audax toties video arma undique verus.",
    "Supplanto defaeco defendo certe textus vulticulus depopulo theca.",
    "Uredo bonus placeat titulus taceo approbo color condico optio viduo.",
    "Aranea depulso absens abstergo quod demulceo triduana temptatio audacia thorax.",
    "Crebro socius defessus tantum tolero ut cavus.",
    "Audentia ustulo anser coaegresco texo argumentum usitas.",
    "Dolores demergo vulnero voluntarius asper.",
    "Tres armarium tersus contra spargo corona amiculum delectatio.",
    "Abeo laudantium adopto cohaero animus admoveo attollo.",
    "Adduco balbus ullam desipio vesco.",
    "Utroque quisquam antepono crastinus incidunt solitudo.",
    "Nobis sint amet aequus angelus sursum illo defero clementia.",
    "Colo ipsum quia admiratio contabesco addo cogo cui vehemens sonitus.",
    "Voluptates caput supplanto vulnero abbas auctus suscipit vix nulla conventus.",
    "Stips volubilis solvo pecus vix voluptates tempora utrimque odit tergum.",
    "Capio comburo suscipit aegrotatio cursus ancilla conforto deporto.",
    "Complectus arx maxime cunabula acervus tactus venio tabesco.",
    "Defleo traho sortitus aegre.",
    "Animadverto demo baiulus tripudio urbs adsuesco traho est.",
    "Approbo caput labore caecus suasoria beatae depereo copia cognomen.",
    "Carmen venia delicate in alveus comprehendo conduco delibero.",
    "Acidus curvo quibusdam deludo sum blandior altus contego uter copiose.",
    "Terga coruscus theca color comptus succedo.",
    "Delicate vomica sulum vomito tumultus tum pecus turpis sopor ultio.",
    "Fuga coniuratio terreo.",
    "Supplanto vomica acidus sumptus.",
    "Caelestis tristis summopere depopulo voluptatibus quos adflicto suscipit tripudio."
  ],
  "imagem": "https://picsum.photos/seed/3W41EzYkzZ/1920/1080",
  "video": "https://loremflickr.com/1920/1080?lock=4445580060101520",
  "slug": "page-490",
  "footer": "Talus laboriosam defleo adimpleo pel sponte denique.",
  "footer2": "Cras claudeo astrum depraedor fuga. Conspergo congregatio tabula tamdiu ea avarus talio. Studio ars aspernatur."
}