{
  "titulo": "Esse surculus amplitudo amet desolo quasi vinculum aeternus vicissitudo stips saepe.",
  "topicos": [
    "Delectus trucido curto.",
    "Crebro vita comes amo impedit quas adnuo.",
    "Celo arguo ratione conventus debilito dicta conculco apto.",
    "Agnosco aetas voluptatem caries venio itaque paens.",
    "Altus aer soluta demum decimus solio acsi audentia angulus crustulum.",
    "Vicissitudo cauda assentator.",
    "Acquiro corroboro tum vespillo verto speculum avaritia.",
    "Vomica tamen vallum dolorum neque acer.",
    "Rem aspernatur compello antepono calcar carcer aequus denuo carpo statim.",
    "Uberrime vesper charisma amiculum benevolentia tandem delectatio vorax sono.",
    "Doloremque sono excepturi.",
    "Contigo vomica arbustum.",
    "Solio ultra dicta tonsor adhaero cedo admoveo vereor.",
    "Strenuus appello atrox amoveo inventore denuncio atrox depono cognatus viridis.",
    "Cui tunc incidunt vester.",
    "Voluptates cavus decor pecus.",
    "Curto cariosus tersus impedit vomica tolero adsum suffoco facere depromo.",
    "Blandior consequuntur architecto ancilla ipsa templum.",
    "Distinctio vester varius desino at cogito convoco sumo denego cotidie.",
    "Assumenda bis turpis.",
    "Excepturi theca vespillo carpo defessus alo tantillus.",
    "Caelum libero curso cognomen tracto architecto absque acies vester delibero.",
    "Vilitas cunae audentia creptio cura blandior.",
    "Coerceo textor tamisium varius consuasor cubo cerno.",
    "Adipisci atrox supellex veniam.",
    "Tersus ubi candidus advoco aperio.",
    "Dolor claustrum adicio defluo cubitum deduco.",
    "Uterque desparatus admitto apto casus.",
    "Nihil triumphus patior facere cognatus curo cultellus.",
    "Caveo verumtamen cernuus trepide vinculum.",
    "Caute viridis aperiam omnis.",
    "Aptus sto depopulo venia cohors adeo confugo veritatis laborum."
  ],
  "imagem": "https://picsum.photos/seed/kXjMK/1920/1080",
  "video": "https://picsum.photos/seed/qdyj3wr/1920/1080",
  "slug": "page-852",
  "footer": "Aeneus cattus substantia uberrime audacia utique suus.",
  "footer2": "Saepe valetudo explicabo delectatio speculum canis aufero. In varietas terebro ustilo averto cetera tui acerbitas vulgus quaerat. Adiuvo veritatis strues earum verto."
}